pydatasummary/__init__.py
pydatasummary/_databackend.py
pydatasummary/_tbl_data.py
pydatasummary/ds.py
pydatasummary-0.0.2.dist-info/LICENSE
pydatasummary-0.0.2.dist-info/METADATA
pydatasummary-0.0.2.dist-info/WHEEL
pydatasummary-0.0.2.dist-info/RECORD
