Metadata-Version: 2.1
Name: pydatasummary
Version: 0.0.2
Summary: Customizable data and model summaries in Python.
Home-page: https://github.com/NKeleher/pydatasummary#readme
License: MIT
Keywords: tables,statistics,econometrics
Author: Niall Keleher
Author-email: niall.keleher@gmail.com
Requires-Python: >=3.9,<4.0
Classifier: Development Status :: 1 - Planning
Classifier: Intended Audience :: Science/Research
Classifier: License :: OSI Approved :: MIT License
Classifier: Programming Language :: Python
Classifier: Programming Language :: Python :: 3
Classifier: Programming Language :: Python :: 3.9
Classifier: Programming Language :: Python :: 3.10
Classifier: Programming Language :: Python :: 3.11
Classifier: Programming Language :: Python :: 3.12
Classifier: Programming Language :: Python :: 3 :: Only
Classifier: Programming Language :: Python :: Implementation :: PyPy
Classifier: Topic :: Scientific/Engineering
Requires-Dist: pandas (>=2.1.4,<3.0.0)
Requires-Dist: polars (>=0.20.5,<0.21.0)
Project-URL: Repository, https://github.com/NKeleher/pydatasummary
